Filhanterare/__init__.py
Filhanterare/hamn.py
Filhanterare-1.0.8.dist-info/LICENSE.txt
Filhanterare-1.0.8.dist-info/METADATA
Filhanterare-1.0.8.dist-info/WHEEL
Filhanterare-1.0.8.dist-info/top_level.txt
Filhanterare-1.0.8.dist-info/RECORD
