Metadata-Version: 2.1
Name: Filhanterare
Version: 1.0.8
Summary: ...
Author: Zeta AI
Author-email: zeta.ai.company@gmail.com
License: MIT
Requires-Python: >=3.7
License-File: LICENSE.txt
